{"results": [{"year": "1991", "bias_name": "Anti-Arab", "count": 1}, {"year": "1991", "bias_name": "Anti-Asian", "count": 6}, {"year": "1991", "bias_name": "Anti-Atheist/Agnosticism", "count": 1}, {"year": "1991", "bias_name": "Anti-Black or African American", "count": 26}, {"year": "1991", "bias_name": "Anti-Female Homosexual (Lesbian)", "count": 2}, {"year": "1991", "bias_name": "Anti-Hispanic or Latino", "count": 7}, {"year": "1991", "bias_name": "Anti-Jewish", "count": 27}, {"year": "1991", "bias_name": "Anti-Male Homosexual (Gay)", "count": 9}, {"year": "1991", "bias_name": "Anti-Not Hispanic or Latino", "count": 2}, {"year": "1991", "bias_name": "Anti-Other Religion", "count": 1}, {"year": "1991", "bias_name": "Anti-White", "count": 14}, {"year": "1992", "bias_name": "Anti-American Indian or Alaska Native", "count": 1}, {"year": "1992", "bias_name": "Anti-Arab", "count": 12}, {"year": "1992", "bias_name": "Anti-Asian", "count": 14}, {"year": "1992", "bias_name": "Anti-Black or African American", "count": 201}, {"year": "1992", "bias_name": "Anti-Female Homosexual (Lesbian)", "count": 4}, {"year": "1992", "bias_name": "Anti-Hispanic or Latino", "count": 23}, {"year": "1992", "bias_name": "Anti-Islamic (Muslem)", "count": 2}, {"year": "1992", "bias_name": "Anti-Jewish", "count": 34}, {"year": "1992", "bias_name": "Anti-Lesbian, Gay, Bisexual, or Transgender, Mixed Group (LGBT)", "count": 10}, {"year": "1992", "bias_name": "Anti-Male Homosexual (Gay)", "count": 45}, {"year": "1992", "bias_name": "Anti-Multi-Racial Group", "count": 12}, {"year": "1992", "bias_name": "Anti-Multi-Religious Group", "count": 1}, {"year": "1992", "bias_name": "Anti-Not Hispanic or Latino", "count": 11}, {"year": "1992", "bias_name": "Anti-Other Religion", "count": 1}, {"year": "1992", "bias_name": "Anti-Protestant", "count": 2}, {"year": "1992", "bias_name": "Anti-White", "count": 114}, {"year": "1993", "bias_name": "Anti-American Indian or Alaska Native", "count": 1}, {"year": "1993", "bias_name": "Anti-Arab", "count": 4}, {"year": "1993", "bias_name": "Anti-Asian", "count": 9}, {"year": "1993", "bias_name": "Anti-Black or African American", "count": 185}, {"year": "1993", "bias_name": "Anti-Catholic", "count": 1}, {"year": "1993", "bias_name": "Anti-Female Homosexual (Lesbian)", "count": 5}, {"year": "1993", "bias_name": "Anti-Heterosexual", "count": 1}, {"year": "1993", "bias_name": "Anti-Hispanic or Latino", "count": 39}, {"year": "1993", "bias_name": "Anti-Jewish", "count": 28}, {"year": "1993", "bias_name": "Anti-Lesbian, Gay, Bisexual, or Transgender, Mixed Group (LGBT)", "count": 6}, {"year": "1993", "bias_name": "Anti-Male Homosexual (Gay)", "count": 36}, {"year": "1993", "bias_name": "Anti-Multi-Racial Group", "count": 3}, {"year": "1993", "bias_name": "Anti-Not Hispanic or Latino", "count": 5}, {"year": "1993", "bias_name": "Anti-Other Religion", "count": 3}, {"year": "1993", "bias_name": "Anti-Protestant", "count": 2}, {"year": "1993", "bias_name": "Anti-White", "count": 90}, {"year": "1994", "bias_name": "Anti-Arab", "count": 5}, {"year": "1994", "bias_name": "Anti-Asian", "count": 16}, {"year": "1994", "bias_name": "Anti-Black or African American", "count": 153}, {"year": "1994", "bias_name": "Anti-Female Homosexual (Lesbian)", "count": 5}, {"year": "1994", "bias_name": "Anti-Hispanic or Latino", "count": 32}, {"year": "1994", "bias_name": "Anti-Jewish", "count": 17}, {"year": "1994", "bias_name": "Anti-Lesbian, Gay, Bisexual, or Transgender, Mixed Group (LGBT)", "count": 7}, {"year": "1994", "bias_name": "Anti-Male Homosexual (Gay)", "count": 48}, {"year": "1994", "bias_name": "Anti-Multi-Racial Group", "count": 4}, {"year": "1994", "bias_name": "Anti-Multi-Religious Group", "count": 1}, {"year": "1994", "bias_name": "Anti-Not Hispanic or Latino", "count": 4}, {"year": "1994", "bias_name": "Anti-Other Religion", "count": 1}, {"year": "1994", "bias_name": "Anti-White", "count": 72}, {"year": "1995", "bias_name": "Anti-Arab", "count": 4}, {"year": "1995", "bias_name": "Anti-Asian", "count": 10}, {"year": "1995", "bias_name": "Anti-Black or African American", "count": 139}, {"year": "1995", "bias_name": "Anti-Catholic", "count": 1}, {"year": "1995", "bias_name": "Anti-Female Homosexual (Lesbian)", "count": 4}, {"year": "1995", "bias_name": "Anti-Hispanic or Latino", "count": 33}, {"year": "1995", "bias_name": "Anti-Islamic (Muslem)", "count": 5}, {"year": "1995", "bias_name": "Anti-Jewish", "count": 20}, {"year": "1995", "bias_name": "Anti-Lesbian, Gay, Bisexual, or Transgender, Mixed Group (LGBT)", "count": 4}, {"year": "1995", "bias_name": "Anti-Male Homosexual (Gay)", "count": 44}, {"year": "1995", "bias_name": "Anti-Multi-Racial Group", "count": 11}, {"year": "1995", "bias_name": "Anti-Not Hispanic or Latino", "count": 4}, {"year": "1995", "bias_name": "Anti-Other Religion", "count": 1}, {"year": "1995", "bias_name": "Anti-White", "count": 46}, {"year": "1996", "bias_name": "Anti-Arab", "count": 3}, {"year": "1996", "bias_name": "Anti-Asian", "count": 6}, {"year": "1996", "bias_name": "Anti-Bisexual", "count": 1}, {"year": "1996", "bias_name": "Anti-Black or African American", "count": 175}, {"year": "1996", "bias_name": "Anti-Female Homosexual (Lesbian)", "count": 13}, {"year": "1996", "bias_name": "Anti-Hispanic or Latino", "count": 36}, {"year": "1996", "bias_name": "Anti-Islamic (Muslem)", "count": 2}, {"year": "1996", "bias_name": "Anti-Jewish", "count": 8}, {"year": "1996", "bias_name": "Anti-Lesbian, Gay, Bisexual, or Transgender, Mixed Group (LGBT)", "count": 3}, {"year": "1996", "bias_name": "Anti-Male Homosexual (Gay)", "count": 45}, {"year": "1996", "bias_name": "Anti-Multi-Racial Group", "count": 8}, {"year": "1996", "bias_name": "Anti-Not Hispanic or Latino", "count": 6}, {"year": "1996", "bias_name": "Anti-White", "count": 44}, {"year": "1997", "bias_name": "Anti-Arab", "count": 2}, {"year": "1997", "bias_name": "Anti-Asian", "count": 11}, {"year": "1997", "bias_name": "Anti-Black or African American", "count": 157}, {"year": "1997", "bias_name": "Anti-Female Homosexual (Lesbian)", "count": 6}, {"year": "1997", "bias_name": "Anti-Hispanic or Latino", "count": 23}, {"year": "1997", "bias_name": "Anti-Islamic (Muslem)", "count": 1}, {"year": "1997", "bias_name": "Anti-Jewish", "count": 20}, {"year": "1997", "bias_name": "Anti-Lesbian, Gay, Bisexual, or Transgender, Mixed Group (LGBT)", "count": 12}, {"year": "1997", "bias_name": "Anti-Male Homosexual (Gay)", "count": 37}, {"year": "1997", "bias_name": "Anti-Mental Disability", "count": 1}, {"year": "1997", "bias_name": "Anti-Multi-Racial Group", "count": 7}, {"year": "1997", "bias_name": "Anti-Multi-Religious Group", "count": 2}, {"year": "1997", "bias_name": "Anti-Not Hispanic or Latino", "count": 4}, {"year": "1997", "bias_name": "Anti-Other Religion", "count": 2}, {"year": "1997", "bias_name": "Anti-Physical Disability", "count": 1}, {"year": "1997", "bias_name": "Anti-Protestant", "count": 7}, {"year": "1997", "bias_name": "Anti-White", "count": 46}, {"year": "1998", "bias_name": "Anti-American Indian or Alaska Native", "count": 1}, {"year": "1998", "bias_name": "Anti-Arab", "count": 2}, {"year": "1998", "bias_name": "Anti-Asian", "count": 10}, {"year": "1998", "bias_name": "Anti-Bisexual", "count": 1}, {"year": "1998", "bias_name": "Anti-Black or African American", "count": 131}, {"year": "1998", "bias_name": "Anti-Female Homosexual (Lesbian)", "count": 11}, {"year": "1998", "bias_name": "Anti-Hispanic or Latino", "count": 28}, {"year": "1998", "bias_name": "Anti-Islamic (Muslem)", "count": 1}, {"year": "1998", "bias_name": "Anti-Jewish", "count": 9}, {"year": "1998", "bias_name": "Anti-Lesbian, Gay, Bisexual, or Transgender, Mixed Group (LGBT)", "count": 7}, {"year": "1998", "bias_name": "Anti-Male Homosexual (Gay)", "count": 40}, {"year": "1998", "bias_name": "Anti-Mental Disability", "count": 3}, {"year": "1998", "bias_name": "Anti-Multi-Racial Group", "count": 8}, {"year": "1998", "bias_name": "Anti-Multi-Religious Group", "count": 6}, {"year": "1998", "bias_name": "Anti-Not Hispanic or Latino", "count": 5}, {"year": "1998", "bias_name": "Anti-Protestant", "count": 7}, {"year": "1998", "bias_name": "Anti-White", "count": 31}, {"year": "1999", "bias_name": "Anti-American Indian or Alaska Native", "count": 3}, {"year": "1999", "bias_name": "Anti-Arab", "count": 6}, {"year": "1999", "bias_name": "Anti-Asian", "count": 2}, {"year": "1999", "bias_name": "Anti-Black or African American", "count": 116}, {"year": "1999", "bias_name": "Anti-Female Homosexual (Lesbian)", "count": 8}, {"year": "1999", "bias_name": "Anti-Hispanic or Latino", "count": 18}, {"year": "1999", "bias_name": "Anti-Islamic (Muslem)", "count": 1}, {"year": "1999", "bias_name": "Anti-Jewish", "count": 16}, {"year": "1999", "bias_name": "Anti-Lesbian, Gay, Bisexual, or Transgender, Mixed Group (LGBT)", "count": 10}, {"year": "1999", "bias_name": "Anti-Male Homosexual (Gay)", "count": 39}, {"year": "1999", "bias_name": "Anti-Multi-Racial Group", "count": 3}, {"year": "1999", "bias_name": "Anti-Multi-Religious Group", "count": 1}, {"year": "1999", "bias_name": "Anti-Other Religion", "count": 4}, {"year": "1999", "bias_name": "Anti-Physical Disability", "count": 1}, {"year": "1999", "bias_name": "Anti-Protestant", "count": 2}, {"year": "1999", "bias_name": "Anti-White", "count": 33}, {"year": "2000", "bias_name": "Anti-American Indian or Alaska Native", "count": 1}, {"year": "2000", "bias_name": "Anti-Arab", "count": 3}, {"year": "2000", "bias_name": "Anti-Asian", "count": 4}, {"year": "2000", "bias_name": "Anti-Bisexual", "count": 1}, {"year": "2000", "bias_name": "Anti-Black or African American", "count": 123}, {"year": "2000", "bias_name": "Anti-Female Homosexual (Lesbian)", "count": 10}, {"year": "2000", "bias_name": "Anti-Hispanic or Latino", "count": 24}, {"year": "2000", "bias_name": "Anti-Islamic (Muslem)", "count": 3}, {"year": "2000", "bias_name": "Anti-Jewish", "count": 26}, {"year": "2000", "bias_name": "Anti-Lesbian, Gay, Bisexual, or Transgender, Mixed Group (LGBT)", "count": 10}, {"year": "2000", "bias_name": "Anti-Male Homosexual (Gay)", "count": 29}, {"year": "2000", "bias_name": "Anti-Multi-Racial Group", "count": 7}, {"year": "2000", "bias_name": "Anti-Multi-Religious Group", "count": 11}, {"year": "2000", "bias_name": "Anti-Not Hispanic or Latino", "count": 3}, {"year": "2000", "bias_name": "Anti-Other Religion", "count": 3}, {"year": "2000", "bias_name": "Anti-Physical Disability", "count": 2}, {"year": "2000", "bias_name": "Anti-Protestant", "count": 3}, {"year": "2000", "bias_name": "Anti-White", "count": 24}, {"year": "2001", "bias_name": "Anti-American Indian or Alaska Native", "count": 1}, {"year": "2001", "bias_name": "Anti-Arab", "count": 56}, {"year": "2001", "bias_name": "Anti-Asian", "count": 10}, {"year": "2001", "bias_name": "Anti-Black or African American", "count": 152}, {"year": "2001", "bias_name": "Anti-Catholic", "count": 1}, {"year": "2001", "bias_name": "Anti-Female Homosexual (Lesbian)", "count": 10}, {"year": "2001", "bias_name": "Anti-Hispanic or Latino", "count": 45}, {"year": "2001", "bias_name": "Anti-Islamic (Muslem)", "count": 28}, {"year": "2001", "bias_name": "Anti-Jewish", "count": 19}, {"year": "2001", "bias_name": "Anti-Lesbian, Gay, Bisexual, or Transgender, Mixed Group (LGBT)", "count": 8}, {"year": "2001", "bias_name": "Anti-Male Homosexual (Gay)", "count": 37}, {"year": "2001", "bias_name": "Anti-Multi-Racial Group", "count": 7}, {"year": "2001", "bias_name": "Anti-Multi-Religious Group", "count": 1}, {"year": "2001", "bias_name": "Anti-Not Hispanic or Latino", "count": 29}, {"year": "2001", "bias_name": "Anti-Other Religion", "count": 3}, {"year": "2001", "bias_name": "Anti-Protestant", "count": 2}, {"year": "2001", "bias_name": "Anti-White", "count": 28}, {"year": "2002", "bias_name": "Anti-Arab", "count": 17}, {"year": "2002", "bias_name": "Anti-Asian", "count": 10}, {"year": "2002", "bias_name": "Anti-Bisexual", "count": 1}, {"year": "2002", "bias_name": "Anti-Black or African American", "count": 128}, {"year": "2002", "bias_name": "Anti-Female Homosexual (Lesbian)", "count": 5}, {"year": "2002", "bias_name": "Anti-Hispanic or Latino", "count": 43}, {"year": "2002", "bias_name": "Anti-Islamic (Muslem)", "count": 11}, {"year": "2002", "bias_name": "Anti-Jewish", "count": 15}, {"year": "2002", "bias_name": "Anti-Lesbian, Gay, Bisexual, or Transgender, Mixed Group (LGBT)", "count": 5}, {"year": "2002", "bias_name": "Anti-Male Homosexual (Gay)", "count": 39}, {"year": "2002", "bias_name": "Anti-Multi-Racial Group", "count": 2}, {"year": "2002", "bias_name": "Anti-Multi-Religious Group", "count": 1}, {"year": "2002", "bias_name": "Anti-Not Hispanic or Latino", "count": 19}, {"year": "2002", "bias_name": "Anti-Other Religion", "count": 4}, {"year": "2002", "bias_name": "Anti-Physical Disability", "count": 2}, {"year": "2002", "bias_name": "Anti-White", "count": 41}, {"year": "2003", "bias_name": "Anti-Arab", "count": 1}, {"year": "2003", "bias_name": "Anti-Asian", "count": 8}, {"year": "2003", "bias_name": "Anti-Black or African American", "count": 119}, {"year": "2003", "bias_name": "Anti-Catholic", "count": 3}, {"year": "2003", "bias_name": "Anti-Female Homosexual (Lesbian)", "count": 6}, {"year": "2003", "bias_name": "Anti-Hispanic or Latino", "count": 28}, {"year": "2003", "bias_name": "Anti-Islamic (Muslem)", "count": 4}, {"year": "2003", "bias_name": "Anti-Jewish", "count": 21}, {"year": "2003", "bias_name": "Anti-Lesbian, Gay, Bisexual, or Transgender, Mixed Group (LGBT)", "count": 7}, {"year": "2003", "bias_name": "Anti-Male Homosexual (Gay)", "count": 41}, {"year": "2003", "bias_name": "Anti-Multi-Racial Group", "count": 4}, {"year": "2003", "bias_name": "Anti-Multi-Religious Group", "count": 1}, {"year": "2003", "bias_name": "Anti-Not Hispanic or Latino", "count": 25}, {"year": "2003", "bias_name": "Anti-Other Religion", "count": 1}, {"year": "2003", "bias_name": "Anti-Protestant", "count": 1}, {"year": "2003", "bias_name": "Anti-White", "count": 20}, {"year": "2004", "bias_name": "Anti-American Indian or Alaska Native", "count": 2}, {"year": "2004", "bias_name": "Anti-Asian", "count": 3}, {"year": "2004", "bias_name": "Anti-Bisexual", "count": 1}, {"year": "2004", "bias_name": "Anti-Black or African American", "count": 112}, {"year": "2004", "bias_name": "Anti-Catholic", "count": 2}, {"year": "2004", "bias_name": "Anti-Female Homosexual (Lesbian)", "count": 10}, {"year": "2004", "bias_name": "Anti-Heterosexual", "count": 1}, {"year": "2004", "bias_name": "Anti-Hispanic or Latino", "count": 28}, {"year": "2004", "bias_name": "Anti-Islamic (Muslem)", "count": 7}, {"year": "2004", "bias_name": "Anti-Jewish", "count": 20}, {"year": "2004", "bias_name": "Anti-Lesbian, Gay, Bisexual, or Transgender, Mixed Group (LGBT)", "count": 6}, {"year": "2004", "bias_name": "Anti-Male Homosexual (Gay)", "count": 36}, {"year": "2004", "bias_name": "Anti-Mental Disability", "count": 1}, {"year": "2004", "bias_name": "Anti-Multi-Racial Group", "count": 2}, {"year": "2004", "bias_name": "Anti-Multi-Religious Group", "count": 3}, {"year": "2004", "bias_name": "Anti-Not Hispanic or Latino", "count": 25}, {"year": "2004", "bias_name": "Anti-Other Religion", "count": 2}, {"year": "2004", "bias_name": "Anti-Physical Disability", "count": 1}, {"year": "2004", "bias_name": "Anti-Protestant", "count": 2}, {"year": "2004", "bias_name": "Anti-White", "count": 34}, {"year": "2005", "bias_name": "Anti-Asian", "count": 7}, {"year": "2005", "bias_name": "Anti-Bisexual", "count": 2}, {"year": "2005", "bias_name": "Anti-Black or African American", "count": 89}, {"year": "2005", "bias_name": "Anti-Female Homosexual (Lesbian)", "count": 9}, {"year": "2005", "bias_name": "Anti-Heterosexual", "count": 1}, {"year": "2005", "bias_name": "Anti-Hispanic or Latino", "count": 24}, {"year": "2005", "bias_name": "Anti-Islamic (Muslem)", "count": 9}, {"year": "2005", "bias_name": "Anti-Jewish", "count": 18}, {"year": "2005", "bias_name": "Anti-Lesbian, Gay, Bisexual, or Transgender, Mixed Group (LGBT)", "count": 9}, {"year": "2005", "bias_name": "Anti-Male Homosexual (Gay)", "count": 42}, {"year": "2005", "bias_name": "Anti-Multi-Racial Group", "count": 3}, {"year": "2005", "bias_name": "Anti-Multi-Religious Group", "count": 2}, {"year": "2005", "bias_name": "Anti-Not Hispanic or Latino", "count": 19}, {"year": "2005", "bias_name": "Anti-Other Religion", "count": 3}, {"year": "2005", "bias_name": "Anti-Protestant", "count": 4}, {"year": "2005", "bias_name": "Anti-White", "count": 23}, {"year": "2006", "bias_name": "Anti-Asian", "count": 4}, {"year": "2006", "bias_name": "Anti-Black or African American", "count": 92}, {"year": "2006", "bias_name": "Anti-Catholic", "count": 1}, {"year": "2006", "bias_name": "Anti-Female Homosexual (Lesbian)", "count": 4}, {"year": "2006", "bias_name": "Anti-Hispanic or Latino", "count": 33}, {"year": "2006", "bias_name": "Anti-Islamic (Muslem)", "count": 5}, {"year": "2006", "bias_name": "Anti-Jewish", "count": 15}, {"year": "2006", "bias_name": "Anti-Lesbian, Gay, Bisexual, or Transgender, Mixed Group (LGBT)", "count": 6}, {"year": "2006", "bias_name": "Anti-Male Homosexual (Gay)", "count": 37}, {"year": "2006", "bias_name": "Anti-Mental Disability", "count": 1}, {"year": "2006", "bias_name": "Anti-Multi-Racial Group", "count": 3}, {"year": "2006", "bias_name": "Anti-Multi-Religious Group", "count": 1}, {"year": "2006", "bias_name": "Anti-Not Hispanic or Latino", "count": 13}, {"year": "2006", "bias_name": "Anti-Other Religion", "count": 3}, {"year": "2006", "bias_name": "Anti-Protestant", "count": 2}, {"year": "2006", "bias_name": "Anti-White", "count": 23}, {"year": "2007", "bias_name": "Anti-American Indian or Alaska Native", "count": 1}, {"year": "2007", "bias_name": "Anti-Asian", "count": 6}, {"year": "2007", "bias_name": "Anti-Black or African American", "count": 102}, {"year": "2007", "bias_name": "Anti-Female Homosexual (Lesbian)", "count": 6}, {"year": "2007", "bias_name": "Anti-Hispanic or Latino", "count": 32}, {"year": "2007", "bias_name": "Anti-Islamic (Muslem)", "count": 4}, {"year": "2007", "bias_name": "Anti-Jewish", "count": 12}, {"year": "2007", "bias_name": "Anti-Lesbian, Gay, Bisexual, or Transgender, Mixed Group (LGBT)", "count": 2}, {"year": "2007", "bias_name": "Anti-Male Homosexual (Gay)", "count": 38}, {"year": "2007", "bias_name": "Anti-Multi-Racial Group", "count": 3}, {"year": "2007", "bias_name": "Anti-Not Hispanic or Latino", "count": 14}, {"year": "2007", "bias_name": "Anti-Other Religion", "count": 3}, {"year": "2007", "bias_name": "Anti-Protestant", "count": 1}, {"year": "2007", "bias_name": "Anti-White", "count": 18}, {"year": "2008", "bias_name": "Anti-Asian", "count": 4}, {"year": "2008", "bias_name": "Anti-Black or African American", "count": 100}, {"year": "2008", "bias_name": "Anti-Catholic", "count": 3}, {"year": "2008", "bias_name": "Anti-Female Homosexual (Lesbian)", "count": 7}, {"year": "2008", "bias_name": "Anti-Hispanic or Latino", "count": 25}, {"year": "2008", "bias_name": "Anti-Islamic (Muslem)", "count": 2}, {"year": "2008", "bias_name": "Anti-Jewish", "count": 10}, {"year": "2008", "bias_name": "Anti-Lesbian, Gay, Bisexual, or Transgender, Mixed Group (LGBT)", "count": 12}, {"year": "2008", "bias_name": "Anti-Male Homosexual (Gay)", "count": 37}, {"year": "2008", "bias_name": "Anti-Multi-Racial Group", "count": 10}, {"year": "2008", "bias_name": "Anti-Not Hispanic or Latino", "count": 10}, {"year": "2008", "bias_name": "Anti-Other Religion", "count": 8}, {"year": "2008", "bias_name": "Anti-Protestant", "count": 2}, {"year": "2008", "bias_name": "Anti-White", "count": 17}, {"year": "2009", "bias_name": "Anti-American Indian or Alaska Native", "count": 1}, {"year": "2009", "bias_name": "Anti-Asian", "count": 2}, {"year": "2009", "bias_name": "Anti-Black or African American", "count": 63}, {"year": "2009", "bias_name": "Anti-Female Homosexual (Lesbian)", "count": 4}, {"year": "2009", "bias_name": "Anti-Hispanic or Latino", "count": 18}, {"year": "2009", "bias_name": "Anti-Islamic (Muslem)", "count": 3}, {"year": "2009", "bias_name": "Anti-Jewish", "count": 9}, {"year": "2009", "bias_name": "Anti-Lesbian, Gay, Bisexual, or Transgender, Mixed Group (LGBT)", "count": 9}, {"year": "2009", "bias_name": "Anti-Male Homosexual (Gay)", "count": 23}, {"year": "2009", "bias_name": "Anti-Multi-Racial Group", "count": 7}, {"year": "2009", "bias_name": "Anti-Multi-Religious Group", "count": 1}, {"year": "2009", "bias_name": "Anti-Not Hispanic or Latino", "count": 9}, {"year": "2009", "bias_name": "Anti-Other Religion", "count": 4}, {"year": "2009", "bias_name": "Anti-Protestant", "count": 1}, {"year": "2009", "bias_name": "Anti-White", "count": 11}, {"year": "2010", "bias_name": "Anti-Asian", "count": 3}, {"year": "2010", "bias_name": "Anti-Bisexual", "count": 1}, {"year": "2010", "bias_name": "Anti-Black or African American", "count": 70}, {"year": "2010", "bias_name": "Anti-Catholic", "count": 1}, {"year": "2010", "bias_name": "Anti-Female Homosexual (Lesbian)", "count": 6}, {"year": "2010", "bias_name": "Anti-Hispanic or Latino", "count": 21}, {"year": "2010", "bias_name": "Anti-Islamic (Muslem)", "count": 7}, {"year": "2010", "bias_name": "Anti-Jewish", "count": 3}, {"year": "2010", "bias_name": "Anti-Lesbian, Gay, Bisexual, or Transgender, Mixed Group (LGBT)", "count": 8}, {"year": "2010", "bias_name": "Anti-Male Homosexual (Gay)", "count": 24}, {"year": "2010", "bias_name": "Anti-Mental Disability", "count": 1}, {"year": "2010", "bias_name": "Anti-Multi-Racial Group", "count": 4}, {"year": "2010", "bias_name": "Anti-Multi-Religious Group", "count": 2}, {"year": "2010", "bias_name": "Anti-Not Hispanic or Latino", "count": 9}, {"year": "2010", "bias_name": "Anti-Other Religion", "count": 3}, {"year": "2010", "bias_name": "Anti-Protestant", "count": 3}, {"year": "2010", "bias_name": "Anti-White", "count": 8}, {"year": "2011", "bias_name": "Anti-Asian", "count": 3}, {"year": "2011", "bias_name": "Anti-Black or African American", "count": 47}, {"year": "2011", "bias_name": "Anti-Catholic", "count": 2}, {"year": "2011", "bias_name": "Anti-Female Homosexual (Lesbian)", "count": 6}, {"year": "2011", "bias_name": "Anti-Hispanic or Latino", "count": 19}, {"year": "2011", "bias_name": "Anti-Islamic (Muslem)", "count": 6}, {"year": "2011", "bias_name": "Anti-Jewish", "count": 7}, {"year": "2011", "bias_name": "Anti-Lesbian, Gay, Bisexual, or Transgender, Mixed Group (LGBT)", "count": 7}, {"year": "2011", "bias_name": "Anti-Male Homosexual (Gay)", "count": 36}, {"year": "2011", "bias_name": "Anti-Mental Disability", "count": 1}, {"year": "2011", "bias_name": "Anti-Multi-Religious Group", "count": 1}, {"year": "2011", "bias_name": "Anti-Not Hispanic or Latino", "count": 8}, {"year": "2011", "bias_name": "Anti-Other Religion", "count": 1}, {"year": "2011", "bias_name": "Anti-Physical Disability", "count": 1}, {"year": "2011", "bias_name": "Anti-Protestant", "count": 2}, {"year": "2011", "bias_name": "Anti-White", "count": 6}, {"year": "2012", "bias_name": "Anti-Asian", "count": 7}, {"year": "2012", "bias_name": "Anti-Black or African American", "count": 52}, {"year": "2012", "bias_name": "Anti-Catholic", "count": 1}, {"year": "2012", "bias_name": "Anti-Female Homosexual (Lesbian)", "count": 10}, {"year": "2012", "bias_name": "Anti-Hispanic or Latino", "count": 19}, {"year": "2012", "bias_name": "Anti-Islamic (Muslem)", "count": 4}, {"year": "2012", "bias_name": "Anti-Jewish", "count": 11}, {"year": "2012", "bias_name": "Anti-Lesbian, Gay, Bisexual, or Transgender, Mixed Group (LGBT)", "count": 10}, {"year": "2012", "bias_name": "Anti-Male Homosexual (Gay)", "count": 35}, {"year": "2012", "bias_name": "Anti-Multi-Racial Group", "count": 2}, {"year": "2012", "bias_name": "Anti-Not Hispanic or Latino", "count": 8}, {"year": "2012", "bias_name": "Anti-Other Religion", "count": 4}, {"year": "2012", "bias_name": "Anti-Protestant", "count": 3}, {"year": "2012", "bias_name": "Anti-White", "count": 9}, {"year": "2013", "bias_name": "Anti-Asian", "count": 4}, {"year": "2013", "bias_name": "Anti-Bisexual", "count": 2}, {"year": "2013", "bias_name": "Anti-Black or African American", "count": 41}, {"year": "2013", "bias_name": "Anti-Female Homosexual (Lesbian)", "count": 4}, {"year": "2013", "bias_name": "Anti-Hispanic or Latino", "count": 16}, {"year": "2013", "bias_name": "Anti-Islamic (Muslem)", "count": 3}, {"year": "2013", "bias_name": "Anti-Jewish", "count": 3}, {"year": "2013", "bias_name": "Anti-Lesbian, Gay, Bisexual, or Transgender, Mixed Group (LGBT)", "count": 10}, {"year": "2013", "bias_name": "Anti-Male Homosexual (Gay)", "count": 28}, {"year": "2013", "bias_name": "Anti-Mental Disability", "count": 2}, {"year": "2013", "bias_name": "Anti-Multi-Racial Group", "count": 1}, {"year": "2013", "bias_name": "Anti-Not Hispanic or Latino", "count": 9}, {"year": "2013", "bias_name": "Anti-Other Religion", "count": 1}, {"year": "2013", "bias_name": "Anti-White", "count": 8}, {"year": "2014", "bias_name": "Anti-Arab", "count": 1}, {"year": "2014", "bias_name": "Anti-Asian", "count": 2}, {"year": "2014", "bias_name": "Anti-Black or African American", "count": 47}, {"year": "2014", "bias_name": "Anti-Catholic", "count": 3}, {"year": "2014", "bias_name": "Anti-Female", "count": 1}, {"year": "2014", "bias_name": "Anti-Female Homosexual (Lesbian)", "count": 6}, {"year": "2014", "bias_name": "Anti-Hispanic or Latino", "count": 13}, {"year": "2014", "bias_name": "Anti-Islamic (Muslem)", "count": 7}, {"year": "2014", "bias_name": "Anti-Jewish", "count": 3}, {"year": "2014", "bias_name": "Anti-Lesbian, Gay, Bisexual, or Transgender, Mixed Group (LGBT)", "count": 8}, {"year": "2014", "bias_name": "Anti-Male Homosexual (Gay)", "count": 26}, {"year": "2014", "bias_name": "Anti-Multi-Religious Group", "count": 1}, {"year": "2014", "bias_name": "Anti-Not Hispanic or Latino", "count": 1}, {"year": "2014", "bias_name": "Anti-Other Religion", "count": 3}, {"year": "2014", "bias_name": "Anti-Protestant", "count": 2}, {"year": "2014", "bias_name": "Anti-Transgender", "count": 2}, {"year": "2014", "bias_name": "Anti-White", "count": 19}, {"year": "2015", "bias_name": "Anti-American Indian or Alaska Native", "count": 2}, {"year": "2015", "bias_name": "Anti-Asian", "count": 6}, {"year": "2015", "bias_name": "Anti-Bisexual", "count": 1}, {"year": "2015", "bias_name": "Anti-Black or African American", "count": 48}, {"year": "2015", "bias_name": "Anti-Catholic", "count": 1}, {"year": "2015", "bias_name": "Anti-Female", "count": 1}, {"year": "2015", "bias_name": "Anti-Female Homosexual (Lesbian)", "count": 6}, {"year": "2015", "bias_name": "Anti-Heterosexual", "count": 1}, {"year": "2015", "bias_name": "Anti-Hispanic or Latino", "count": 15}, {"year": "2015", "bias_name": "Anti-Islamic (Muslem)", "count": 16}, {"year": "2015", "bias_name": "Anti-Jewish", "count": 12}, {"year": "2015", "bias_name": "Anti-Lesbian, Gay, Bisexual, or Transgender, Mixed Group (LGBT)", "count": 6}, {"year": "2015", "bias_name": "Anti-Male Homosexual (Gay)", "count": 27}, {"year": "2015", "bias_name": "Anti-Mental Disability", "count": 1}, {"year": "2015", "bias_name": "Anti-Multi-Racial Group", "count": 4}, {"year": "2015", "bias_name": "Anti-Multi-Religious Group", "count": 2}, {"year": "2015", "bias_name": "Anti-Not Hispanic or Latino", "count": 11}, {"year": "2015", "bias_name": "Anti-Other Religion", "count": 5}, {"year": "2015", "bias_name": "Anti-Protestant", "count": 1}, {"year": "2015", "bias_name": "Anti-Transgender", "count": 5}, {"year": "2015", "bias_name": "Anti-White", "count": 23}, {"year": "2002", "bias_name": "Anti-Other Christian", "count": null}, {"year": "2003", "bias_name": "Anti-Other Christian", "count": null}, {"year": "2004", "bias_name": "Anti-Other Christian", "count": null}, {"year": "2005", "bias_name": "Anti-Other Christian", "count": null}, {"year": "2006", "bias_name": "Anti-Other Christian", "count": null}, {"year": "2007", "bias_name": "Anti-Other Christian", "count": null}, {"year": "2008", "bias_name": "Anti-Other Christian", "count": null}, {"year": "2009", "bias_name": "Anti-Other Christian", "count": null}, {"year": "2010", "bias_name": "Anti-Other Christian", "count": null}, {"year": "2011", "bias_name": "Anti-Other Christian", "count": null}, {"year": "2012", "bias_name": "Anti-Other Christian", "count": null}, {"year": "2013", "bias_name": "Anti-Other Christian", "count": null}, {"year": "2014", "bias_name": "Anti-Other Christian", "count": null}, {"year": "2015", "bias_name": "Anti-Other Christian", "count": null}, {"year": "2016", "bias_name": "Anti-Other Christian", "count": null}, {"year": "1996", "bias_name": "Anti-Other Religion", "count": null}, {"year": "1998", "bias_name": "Anti-Other Religion", "count": null}, {"year": "2016", "bias_name": "Anti-Other Religion", "count": null}, {"year": "1991", "bias_name": "Anti-Physical Disability", "count": null}, {"year": "1992", "bias_name": "Anti-Physical Disability", "count": null}, {"year": "1993", "bias_name": "Anti-Physical Disability", "count": null}, {"year": "1994", "bias_name": "Anti-Physical Disability", "count": null}, {"year": "1995", "bias_name": "Anti-Physical Disability", "count": null}, {"year": "1996", "bias_name": "Anti-Physical Disability", "count": null}, {"year": "1998", "bias_name": "Anti-Physical Disability", "count": null}, {"year": "2001", "bias_name": "Anti-Physical Disability", "count": null}, {"year": "2003", "bias_name": "Anti-Physical Disability", "count": null}, {"year": "2005", "bias_name": "Anti-Physical Disability", "count": null}, {"year": "2006", "bias_name": "Anti-Physical Disability", "count": null}, {"year": "2007", "bias_name": "Anti-Physical Disability", "count": null}, {"year": "2008", "bias_name": "Anti-Physical Disability", "count": null}, {"year": "2009", "bias_name": "Anti-Physical Disability", "count": null}, {"year": "2010", "bias_name": "Anti-Physical Disability", "count": null}, {"year": "2012", "bias_name": "Anti-Physical Disability", "count": null}, {"year": "2013", "bias_name": "Anti-Physical Disability", "count": null}, {"year": "2014", "bias_name": "Anti-Physical Disability", "count": null}, {"year": "2015", "bias_name": "Anti-Physical Disability", "count": null}, {"year": "2016", "bias_name": "Anti-Physical Disability", "count": null}, {"year": "1991", "bias_name": "Anti-Protestant", "count": null}, {"year": "1994", "bias_name": "Anti-Protestant", "count": null}, {"year": "1995", "bias_name": "Anti-Protestant", "count": null}, {"year": "1996", "bias_name": "Anti-Protestant", "count": null}, {"year": "2002", "bias_name": "Anti-Protestant", "count": null}, {"year": "2013", "bias_name": "Anti-Protestant", "count": null}, {"year": "2016", "bias_name": "Anti-Protestant", "count": null}, {"year": "1991", "bias_name": "Anti-Sikh", "count": null}, {"year": "1992", "bias_name": "Anti-Sikh", "count": null}, {"year": "1993", "bias_name": "Anti-Sikh", "count": null}, {"year": "1994", "bias_name": "Anti-Sikh", "count": null}, {"year": "1995", "bias_name": "Anti-Sikh", "count": null}, {"year": "1996", "bias_name": "Anti-Sikh", "count": null}, {"year": "1997", "bias_name": "Anti-Sikh", "count": null}, {"year": "1998", "bias_name": "Anti-Sikh", "count": null}, {"year": "1999", "bias_name": "Anti-Sikh", "count": null}, {"year": "2000", "bias_name": "Anti-Sikh", "count": null}, {"year": "2001", "bias_name": "Anti-Sikh", "count": null}, {"year": "2002", "bias_name": "Anti-Sikh", "count": null}, {"year": "2003", "bias_name": "Anti-Sikh", "count": null}, {"year": "2004", "bias_name": "Anti-Sikh", "count": null}, {"year": "2005", "bias_name": "Anti-Sikh", "count": null}, {"year": "2006", "bias_name": "Anti-Sikh", "count": null}, {"year": "2007", "bias_name": "Anti-Sikh", "count": null}, {"year": "2008", "bias_name": "Anti-Sikh", "count": null}, {"year": "2009", "bias_name": "Anti-Sikh", "count": null}, {"year": "2010", "bias_name": "Anti-Sikh", "count": null}, {"year": "2011", "bias_name": "Anti-Sikh", "count": null}, {"year": "2012", "bias_name": "Anti-Sikh", "count": null}, {"year": "2013", "bias_name": "Anti-Sikh", "count": null}, {"year": "2014", "bias_name": "Anti-Sikh", "count": null}, {"year": "2015", "bias_name": "Anti-Sikh", "count": null}, {"year": "2016", "bias_name": "Anti-Sikh", "count": null}, {"year": "1991", "bias_name": "Anti-Transgender", "count": null}, {"year": "1992", "bias_name": "Anti-Transgender", "count": null}, {"year": "1993", "bias_name": "Anti-Transgender", "count": null}, {"year": "1994", "bias_name": "Anti-Transgender", "count": null}, {"year": "1995", "bias_name": "Anti-Transgender", "count": null}, {"year": "1996", "bias_name": "Anti-Transgender", "count": null}, {"year": "1997", "bias_name": "Anti-Transgender", "count": null}, {"year": "1998", "bias_name": "Anti-Transgender", "count": null}, {"year": "1999", "bias_name": "Anti-Transgender", "count": null}, {"year": "2000", "bias_name": "Anti-Transgender", "count": null}, {"year": "2001", "bias_name": "Anti-Transgender", "count": null}, {"year": "2002", "bias_name": "Anti-Transgender", "count": null}, {"year": "2003", "bias_name": "Anti-Transgender", "count": null}, {"year": "2004", "bias_name": "Anti-Transgender", "count": null}, {"year": "2005", "bias_name": "Anti-Transgender", "count": null}, {"year": "2006", "bias_name": "Anti-Transgender", "count": null}, {"year": "2007", "bias_name": "Anti-Transgender", "count": null}, {"year": "2008", "bias_name": "Anti-Transgender", "count": null}, {"year": "2009", "bias_name": "Anti-Transgender", "count": null}, {"year": "2010", "bias_name": "Anti-Transgender", "count": null}, {"year": "2011", "bias_name": "Anti-Transgender", "count": null}, {"year": "2012", "bias_name": "Anti-Transgender", "count": null}, {"year": "2013", "bias_name": "Anti-Transgender", "count": null}, {"year": "2016", "bias_name": "Anti-Transgender", "count": null}, {"year": "2016", "bias_name": "Anti-White", "count": null}, {"year": "1991", "bias_name": "None", "count": null}, {"year": "1992", "bias_name": "None", "count": null}, {"year": "1993", "bias_name": "None", "count": null}, {"year": "1994", "bias_name": "None", "count": null}, {"year": "1995", "bias_name": "None", "count": null}, {"year": "1996", "bias_name": "None", "count": null}, {"year": "1997", "bias_name": "None", "count": null}, {"year": "1998", "bias_name": "None", "count": null}, {"year": "1999", "bias_name": "None", "count": null}, {"year": "2000", "bias_name": "None", "count": null}, {"year": "2001", "bias_name": "None", "count": null}, {"year": "2002", "bias_name": "None", "count": null}, {"year": "2003", "bias_name": "None", "count": null}, {"year": "2004", "bias_name": "None", "count": null}, {"year": "2005", "bias_name": "None", "count": null}, {"year": "2006", "bias_name": "None", "count": null}, {"year": "2007", "bias_name": "None", "count": null}, {"year": "2008", "bias_name": "None", "count": null}, {"year": "2009", "bias_name": "None", "count": null}, {"year": "2010", "bias_name": "None", "count": null}, {"year": "2011", "bias_name": "None", "count": null}, {"year": "2012", "bias_name": "None", "count": null}, {"year": "2013", "bias_name": "None", "count": null}, {"year": "2014", "bias_name": "None", "count": null}, {"year": "2015", "bias_name": "None", "count": null}, {"year": "2016", "bias_name": "None", "count": null}, {"year": "1991", "bias_name": "Unknown", "count": null}, {"year": "1992", "bias_name": "Unknown", "count": null}, {"year": "1993", "bias_name": "Unknown", "count": null}, {"year": "1994", "bias_name": "Unknown", "count": null}, {"year": "1995", "bias_name": "Unknown", "count": null}, {"year": "1996", "bias_name": "Unknown", "count": null}, {"year": "1997", "bias_name": "Unknown", "count": null}, {"year": "1998", "bias_name": "Unknown", "count": null}, {"year": "1999", "bias_name": "Unknown", "count": null}, {"year": "2000", "bias_name": "Unknown", "count": null}, {"year": "2001", "bias_name": "Unknown", "count": null}, {"year": "2002", "bias_name": "Unknown", "count": null}, {"year": "2003", "bias_name": "Unknown", "count": null}, {"year": "2004", "bias_name": "Unknown", "count": null}, {"year": "2005", "bias_name": "Unknown", "count": null}, {"year": "2006", "bias_name": "Unknown", "count": null}, {"year": "2007", "bias_name": "Unknown", "count": null}, {"year": "2008", "bias_name": "Unknown", "count": null}, {"year": "2009", "bias_name": "Unknown", "count": null}, {"year": "2010", "bias_name": "Unknown", "count": null}, {"year": "2011", "bias_name": "Unknown", "count": null}, {"year": "2012", "bias_name": "Unknown", "count": null}, {"year": "2013", "bias_name": "Unknown", "count": null}, {"year": "2014", "bias_name": "Unknown", "count": null}, {"year": "2015", "bias_name": "Unknown", "count": null}, {"year": "1991", "bias_name": "Anti-American Indian or Alaska Native", "count": null}, {"year": "2016", "bias_name": "Unknown", "count": null}, {"year": "1994", "bias_name": "Anti-American Indian or Alaska Native", "count": null}, {"year": "1995", "bias_name": "Anti-American Indian or Alaska Native", "count": null}, {"year": "1996", "bias_name": "Anti-American Indian or Alaska Native", "count": null}, {"year": "1997", "bias_name": "Anti-American Indian or Alaska Native", "count": null}, {"year": "2002", "bias_name": "Anti-American Indian or Alaska Native", "count": null}, {"year": "2003", "bias_name": "Anti-American Indian or Alaska Native", "count": null}, {"year": "2005", "bias_name": "Anti-American Indian or Alaska Native", "count": null}, {"year": "2006", "bias_name": "Anti-American Indian or Alaska Native", "count": null}, {"year": "2008", "bias_name": "Anti-American Indian or Alaska Native", "count": null}, {"year": "2010", "bias_name": "Anti-American Indian or Alaska Native", "count": null}, {"year": "2011", "bias_name": "Anti-American Indian or Alaska Native", "count": null}, {"year": "2012", "bias_name": "Anti-American Indian or Alaska Native", "count": null}, {"year": "2013", "bias_name": "Anti-American Indian or Alaska Native", "count": null}, {"year": "2014", "bias_name": "Anti-American Indian or Alaska Native", "count": null}, {"year": "2016", "bias_name": "Anti-American Indian or Alaska Native", "count": null}, {"year": "2004", "bias_name": "Anti-Arab", "count": null}, {"year": "2005", "bias_name": "Anti-Arab", "count": null}, {"year": "2006", "bias_name": "Anti-Arab", "count": null}, {"year": "2007", "bias_name": "Anti-Arab", "count": null}, {"year": "2008", "bias_name": "Anti-Arab", "count": null}, {"year": "2009", "bias_name": "Anti-Arab", "count": null}, {"year": "2010", "bias_name": "Anti-Arab", "count": null}, {"year": "2011", "bias_name": "Anti-Arab", "count": null}, {"year": "2012", "bias_name": "Anti-Arab", "count": null}, {"year": "2013", "bias_name": "Anti-Arab", "count": null}, {"year": "2015", "bias_name": "Anti-Arab", "count": null}, {"year": "2016", "bias_name": "Anti-Arab", "count": null}, {"year": "2016", "bias_name": "Anti-Asian", "count": null}, {"year": "1992", "bias_name": "Anti-Atheist/Agnosticism", "count": null}, {"year": "1993", "bias_name": "Anti-Atheist/Agnosticism", "count": null}, {"year": "1994", "bias_name": "Anti-Atheist/Agnosticism", "count": null}, {"year": "1995", "bias_name": "Anti-Atheist/Agnosticism", "count": null}, {"year": "1996", "bias_name": "Anti-Atheist/Agnosticism", "count": null}, {"year": "1997", "bias_name": "Anti-Atheist/Agnosticism", "count": null}, {"year": "1998", "bias_name": "Anti-Atheist/Agnosticism", "count": null}, {"year": "1999", "bias_name": "Anti-Atheist/Agnosticism", "count": null}, {"year": "2000", "bias_name": "Anti-Atheist/Agnosticism", "count": null}, {"year": "2001", "bias_name": "Anti-Atheist/Agnosticism", "count": null}, {"year": "2002", "bias_name": "Anti-Atheist/Agnosticism", "count": null}, {"year": "2003", "bias_name": "Anti-Atheist/Agnosticism", "count": null}, {"year": "2004", "bias_name": "Anti-Atheist/Agnosticism", "count": null}, {"year": "2005", "bias_name": "Anti-Atheist/Agnosticism", "count": null}, {"year": "2006", "bias_name": "Anti-Atheist/Agnosticism", "count": null}, {"year": "2007", "bias_name": "Anti-Atheist/Agnosticism", "count": null}, {"year": "2008", "bias_name": "Anti-Atheist/Agnosticism", "count": null}, {"year": "2009", "bias_name": "Anti-Atheist/Agnosticism", "count": null}, {"year": "2010", "bias_name": "Anti-Atheist/Agnosticism", "count": null}, {"year": "2011", "bias_name": "Anti-Atheist/Agnosticism", "count": null}, {"year": "2012", "bias_name": "Anti-Atheist/Agnosticism", "count": null}, {"year": "2013", "bias_name": "Anti-Atheist/Agnosticism", "count": null}, {"year": "2014", "bias_name": "Anti-Atheist/Agnosticism", "count": null}, {"year": "2015", "bias_name": "Anti-Atheist/Agnosticism", "count": null}, {"year": "2016", "bias_name": "Anti-Atheist/Agnosticism", "count": null}, {"year": "1991", "bias_name": "Anti-Bisexual", "count": null}, {"year": "1992", "bias_name": "Anti-Bisexual", "count": null}, {"year": "1993", "bias_name": "Anti-Bisexual", "count": null}, {"year": "1994", "bias_name": "Anti-Bisexual", "count": null}, {"year": "1995", "bias_name": "Anti-Bisexual", "count": null}, {"year": "1997", "bias_name": "Anti-Bisexual", "count": null}, {"year": "1999", "bias_name": "Anti-Bisexual", "count": null}, {"year": "2001", "bias_name": "Anti-Bisexual", "count": null}, {"year": "2003", "bias_name": "Anti-Bisexual", "count": null}, {"year": "2006", "bias_name": "Anti-Bisexual", "count": null}, {"year": "2007", "bias_name": "Anti-Bisexual", "count": null}, {"year": "2008", "bias_name": "Anti-Bisexual", "count": null}, {"year": "2009", "bias_name": "Anti-Bisexual", "count": null}, {"year": "2011", "bias_name": "Anti-Bisexual", "count": null}, {"year": "2012", "bias_name": "Anti-Bisexual", "count": null}, {"year": "2014", "bias_name": "Anti-Bisexual", "count": null}, {"year": "2016", "bias_name": "Anti-Bisexual", "count": null}, {"year": "2016", "bias_name": "Anti-Black or African American", "count": null}, {"year": "1991", "bias_name": "Anti-Buddhist", "count": null}, {"year": "1992", "bias_name": "Anti-Buddhist", "count": null}, {"year": "1993", "bias_name": "Anti-Buddhist", "count": null}, {"year": "1994", "bias_name": "Anti-Buddhist", "count": null}, {"year": "1995", "bias_name": "Anti-Buddhist", "count": null}, {"year": "1996", "bias_name": "Anti-Buddhist", "count": null}, {"year": "1997", "bias_name": "Anti-Buddhist", "count": null}, {"year": "1998", "bias_name": "Anti-Buddhist", "count": null}, {"year": "1999", "bias_name": "Anti-Buddhist", "count": null}, {"year": "2000", "bias_name": "Anti-Buddhist", "count": null}, {"year": "2001", "bias_name": "Anti-Buddhist", "count": null}, {"year": "2002", "bias_name": "Anti-Buddhist", "count": null}, {"year": "2003", "bias_name": "Anti-Buddhist", "count": null}, {"year": "2004", "bias_name": "Anti-Buddhist", "count": null}, {"year": "2005", "bias_name": "Anti-Buddhist", "count": null}, {"year": "2006", "bias_name": "Anti-Buddhist", "count": null}, {"year": "2007", "bias_name": "Anti-Buddhist", "count": null}, {"year": "2008", "bias_name": "Anti-Buddhist", "count": null}, {"year": "2009", "bias_name": "Anti-Buddhist", "count": null}, {"year": "2010", "bias_name": "Anti-Buddhist", "count": null}, {"year": "2011", "bias_name": "Anti-Buddhist", "count": null}, {"year": "2012", "bias_name": "Anti-Buddhist", "count": null}, {"year": "2013", "bias_name": "Anti-Buddhist", "count": null}, {"year": "2014", "bias_name": "Anti-Buddhist", "count": null}, {"year": "2015", "bias_name": "Anti-Buddhist", "count": null}, {"year": "2016", "bias_name": "Anti-Buddhist", "count": null}, {"year": "1991", "bias_name": "Anti-Catholic", "count": null}, {"year": "1992", "bias_name": "Anti-Catholic", "count": null}, {"year": "1994", "bias_name": "Anti-Catholic", "count": null}, {"year": "1996", "bias_name": "Anti-Catholic", "count": null}, {"year": "1997", "bias_name": "Anti-Catholic", "count": null}, {"year": "1998", "bias_name": "Anti-Catholic", "count": null}, {"year": "1999", "bias_name": "Anti-Catholic", "count": null}, {"year": "2000", "bias_name": "Anti-Catholic", "count": null}, {"year": "2002", "bias_name": "Anti-Catholic", "count": null}, {"year": "2005", "bias_name": "Anti-Catholic", "count": null}, {"year": "2007", "bias_name": "Anti-Catholic", "count": null}, {"year": "2009", "bias_name": "Anti-Catholic", "count": null}, {"year": "2013", "bias_name": "Anti-Catholic", "count": null}, {"year": "2016", "bias_name": "Anti-Catholic", "count": null}, {"year": "1991", "bias_name": "Anti-Eastern Orthodox", "count": null}, {"year": "1992", "bias_name": "Anti-Eastern Orthodox", "count": null}, {"year": "1993", "bias_name": "Anti-Eastern Orthodox", "count": null}, {"year": "1994", "bias_name": "Anti-Eastern Orthodox", "count": null}, {"year": "1995", "bias_name": "Anti-Eastern Orthodox", "count": null}, {"year": "1996", "bias_name": "Anti-Eastern Orthodox", "count": null}, {"year": "1997", "bias_name": "Anti-Eastern Orthodox", "count": null}, {"year": "1998", "bias_name": "Anti-Eastern Orthodox", "count": null}, {"year": "1999", "bias_name": "Anti-Eastern Orthodox", "count": null}, {"year": "2000", "bias_name": "Anti-Eastern Orthodox", "count": null}, {"year": "2001", "bias_name": "Anti-Eastern Orthodox", "count": null}, {"year": "2002", "bias_name": "Anti-Eastern Orthodox", "count": null}, {"year": "2003", "bias_name": "Anti-Eastern Orthodox", "count": null}, {"year": "2004", "bias_name": "Anti-Eastern Orthodox", "count": null}, {"year": "2005", "bias_name": "Anti-Eastern Orthodox", "count": null}, {"year": "2006", "bias_name": "Anti-Eastern Orthodox", "count": null}, {"year": "2007", "bias_name": "Anti-Eastern Orthodox", "count": null}, {"year": "2008", "bias_name": "Anti-Eastern Orthodox", "count": null}, {"year": "2009", "bias_name": "Anti-Eastern Orthodox", "count": null}, {"year": "2010", "bias_name": "Anti-Eastern Orthodox", "count": null}, {"year": "2011", "bias_name": "Anti-Eastern Orthodox", "count": null}, {"year": "2012", "bias_name": "Anti-Eastern Orthodox", "count": null}, {"year": "2013", "bias_name": "Anti-Eastern Orthodox", "count": null}, {"year": "2014", "bias_name": "Anti-Eastern Orthodox", "count": null}, {"year": "2015", "bias_name": "Anti-Eastern Orthodox", "count": null}, {"year": "2016", "bias_name": "Anti-Eastern Orthodox", "count": null}, {"year": "1991", "bias_name": "Anti-Female", "count": null}, {"year": "1992", "bias_name": "Anti-Female", "count": null}, {"year": "1993", "bias_name": "Anti-Female", "count": null}, {"year": "1994", "bias_name": "Anti-Female", "count": null}, {"year": "1995", "bias_name": "Anti-Female", "count": null}, {"year": "1996", "bias_name": "Anti-Female", "count": null}, {"year": "1997", "bias_name": "Anti-Female", "count": null}, {"year": "1998", "bias_name": "Anti-Female", "count": null}, {"year": "1999", "bias_name": "Anti-Female", "count": null}, {"year": "2000", "bias_name": "Anti-Female", "count": null}, {"year": "2001", "bias_name": "Anti-Female", "count": null}, {"year": "2002", "bias_name": "Anti-Female", "count": null}, {"year": "2003", "bias_name": "Anti-Female", "count": null}, {"year": "2004", "bias_name": "Anti-Female", "count": null}, {"year": "2005", "bias_name": "Anti-Female", "count": null}, {"year": "2006", "bias_name": "Anti-Female", "count": null}, {"year": "2007", "bias_name": "Anti-Female", "count": null}, {"year": "2008", "bias_name": "Anti-Female", "count": null}, {"year": "2009", "bias_name": "Anti-Female", "count": null}, {"year": "2010", "bias_name": "Anti-Female", "count": null}, {"year": "2011", "bias_name": "Anti-Female", "count": null}, {"year": "2012", "bias_name": "Anti-Female", "count": null}, {"year": "2013", "bias_name": "Anti-Female", "count": null}, {"year": "2016", "bias_name": "Anti-Female", "count": null}, {"year": "2016", "bias_name": "Anti-Female Homosexual (Lesbian)", "count": null}, {"year": "1991", "bias_name": "Anti-Gender Non-Conforming", "count": null}, {"year": "1992", "bias_name": "Anti-Gender Non-Conforming", "count": null}, {"year": "1993", "bias_name": "Anti-Gender Non-Conforming", "count": null}, {"year": "1994", "bias_name": "Anti-Gender Non-Conforming", "count": null}, {"year": "1995", "bias_name": "Anti-Gender Non-Conforming", "count": null}, {"year": "1996", "bias_name": "Anti-Gender Non-Conforming", "count": null}, {"year": "1997", "bias_name": "Anti-Gender Non-Conforming", "count": null}, {"year": "1998", "bias_name": "Anti-Gender Non-Conforming", "count": null}, {"year": "1999", "bias_name": "Anti-Gender Non-Conforming", "count": null}, {"year": "2000", "bias_name": "Anti-Gender Non-Conforming", "count": null}, {"year": "2001", "bias_name": "Anti-Gender Non-Conforming", "count": null}, {"year": "2002", "bias_name": "Anti-Gender Non-Conforming", "count": null}, {"year": "2003", "bias_name": "Anti-Gender Non-Conforming", "count": null}, {"year": "2004", "bias_name": "Anti-Gender Non-Conforming", "count": null}, {"year": "2005", "bias_name": "Anti-Gender Non-Conforming", "count": null}, {"year": "2006", "bias_name": "Anti-Gender Non-Conforming", "count": null}, {"year": "2007", "bias_name": "Anti-Gender Non-Conforming", "count": null}, {"year": "2008", "bias_name": "Anti-Gender Non-Conforming", "count": null}, {"year": "2009", "bias_name": "Anti-Gender Non-Conforming", "count": null}, {"year": "2010", "bias_name": "Anti-Gender Non-Conforming", "count": null}, {"year": "2011", "bias_name": "Anti-Gender Non-Conforming", "count": null}, {"year": "2012", "bias_name": "Anti-Gender Non-Conforming", "count": null}, {"year": "2013", "bias_name": "Anti-Gender Non-Conforming", "count": null}, {"year": "2014", "bias_name": "Anti-Gender Non-Conforming", "count": null}, {"year": "2015", "bias_name": "Anti-Gender Non-Conforming", "count": null}, {"year": "2016", "bias_name": "Anti-Gender Non-Conforming", "count": null}, {"year": "1991", "bias_name": "Anti-Heterosexual", "count": null}, {"year": "1992", "bias_name": "Anti-Heterosexual", "count": null}, {"year": "1994", "bias_name": "Anti-Heterosexual", "count": null}, {"year": "1995", "bias_name": "Anti-Heterosexual", "count": null}, {"year": "1996", "bias_name": "Anti-Heterosexual", "count": null}, {"year": "1997", "bias_name": "Anti-Heterosexual", "count": null}, {"year": "1998", "bias_name": "Anti-Heterosexual", "count": null}, {"year": "1999", "bias_name": "Anti-Heterosexual", "count": null}, {"year": "2000", "bias_name": "Anti-Heterosexual", "count": null}, {"year": "2001", "bias_name": "Anti-Heterosexual", "count": null}, {"year": "2002", "bias_name": "Anti-Heterosexual", "count": null}, {"year": "2003", "bias_name": "Anti-Heterosexual", "count": null}, {"year": "2006", "bias_name": "Anti-Heterosexual", "count": null}, {"year": "2007", "bias_name": "Anti-Heterosexual", "count": null}, {"year": "2008", "bias_name": "Anti-Heterosexual", "count": null}, {"year": "2009", "bias_name": "Anti-Heterosexual", "count": null}, {"year": "2010", "bias_name": "Anti-Heterosexual", "count": null}, {"year": "2011", "bias_name": "Anti-Heterosexual", "count": null}, {"year": "2012", "bias_name": "Anti-Heterosexual", "count": null}, {"year": "2013", "bias_name": "Anti-Heterosexual", "count": null}, {"year": "2014", "bias_name": "Anti-Heterosexual", "count": null}, {"year": "2016", "bias_name": "Anti-Heterosexual", "count": null}, {"year": "1991", "bias_name": "Anti-Hindu", "count": null}, {"year": "1992", "bias_name": "Anti-Hindu", "count": null}, {"year": "1993", "bias_name": "Anti-Hindu", "count": null}, {"year": "1994", "bias_name": "Anti-Hindu", "count": null}, {"year": "1995", "bias_name": "Anti-Hindu", "count": null}, {"year": "1996", "bias_name": "Anti-Hindu", "count": null}, {"year": "1997", "bias_name": "Anti-Hindu", "count": null}, {"year": "1998", "bias_name": "Anti-Hindu", "count": null}, {"year": "1999", "bias_name": "Anti-Hindu", "count": null}, {"year": "2000", "bias_name": "Anti-Hindu", "count": null}, {"year": "2001", "bias_name": "Anti-Hindu", "count": null}, {"year": "2002", "bias_name": "Anti-Hindu", "count": null}, {"year": "2003", "bias_name": "Anti-Hindu", "count": null}, {"year": "2004", "bias_name": "Anti-Hindu", "count": null}, {"year": "2005", "bias_name": "Anti-Hindu", "count": null}, {"year": "2006", "bias_name": "Anti-Hindu", "count": null}, {"year": "2007", "bias_name": "Anti-Hindu", "count": null}, {"year": "2008", "bias_name": "Anti-Hindu", "count": null}, {"year": "2009", "bias_name": "Anti-Hindu", "count": null}, {"year": "2010", "bias_name": "Anti-Hindu", "count": null}, {"year": "2011", "bias_name": "Anti-Hindu", "count": null}, {"year": "2012", "bias_name": "Anti-Hindu", "count": null}, {"year": "2013", "bias_name": "Anti-Hindu", "count": null}, {"year": "2014", "bias_name": "Anti-Hindu", "count": null}, {"year": "2015", "bias_name": "Anti-Hindu", "count": null}, {"year": "2016", "bias_name": "Anti-Hindu", "count": null}, {"year": "2016", "bias_name": "Anti-Hispanic or Latino", "count": null}, {"year": "1991", "bias_name": "Anti-Islamic (Muslem)", "count": null}, {"year": "1993", "bias_name": "Anti-Islamic (Muslem)", "count": null}, {"year": "1994", "bias_name": "Anti-Islamic (Muslem)", "count": null}, {"year": "2016", "bias_name": "Anti-Islamic (Muslem)", "count": null}, {"year": "1991", "bias_name": "Anti-Jehovah's Witness", "count": null}, {"year": "1992", "bias_name": "Anti-Jehovah's Witness", "count": null}, {"year": "1993", "bias_name": "Anti-Jehovah's Witness", "count": null}, {"year": "1994", "bias_name": "Anti-Jehovah's Witness", "count": null}, {"year": "1995", "bias_name": "Anti-Jehovah's Witness", "count": null}, {"year": "1996", "bias_name": "Anti-Jehovah's Witness", "count": null}, {"year": "1997", "bias_name": "Anti-Jehovah's Witness", "count": null}, {"year": "1998", "bias_name": "Anti-Jehovah's Witness", "count": null}, {"year": "1999", "bias_name": "Anti-Jehovah's Witness", "count": null}, {"year": "2000", "bias_name": "Anti-Jehovah's Witness", "count": null}, {"year": "2001", "bias_name": "Anti-Jehovah's Witness", "count": null}, {"year": "2002", "bias_name": "Anti-Jehovah's Witness", "count": null}, {"year": "2003", "bias_name": "Anti-Jehovah's Witness", "count": null}, {"year": "2004", "bias_name": "Anti-Jehovah's Witness", "count": null}, {"year": "2005", "bias_name": "Anti-Jehovah's Witness", "count": null}, {"year": "2006", "bias_name": "Anti-Jehovah's Witness", "count": null}, {"year": "2007", "bias_name": "Anti-Jehovah's Witness", "count": null}, {"year": "2008", "bias_name": "Anti-Jehovah's Witness", "count": null}, {"year": "2009", "bias_name": "Anti-Jehovah's Witness", "count": null}, {"year": "2010", "bias_name": "Anti-Jehovah's Witness", "count": null}, {"year": "2011", "bias_name": "Anti-Jehovah's Witness", "count": null}, {"year": "2012", "bias_name": "Anti-Jehovah's Witness", "count": null}, {"year": "2013", "bias_name": "Anti-Jehovah's Witness", "count": null}, {"year": "2014", "bias_name": "Anti-Jehovah's Witness", "count": null}, {"year": "2015", "bias_name": "Anti-Jehovah's Witness", "count": null}, {"year": "2016", "bias_name": "Anti-Jehovah's Witness", "count": null}, {"year": "2016", "bias_name": "Anti-Jewish", "count": null}, {"year": "1991", "bias_name": "Anti-Lesbian, Gay, Bisexual, or Transgender, Mixed Group (LGBT)", "count": null}, {"year": "2016", "bias_name": "Anti-Lesbian, Gay, Bisexual, or Transgender, Mixed Group (LGBT)", "count": null}, {"year": "1991", "bias_name": "Anti-Male", "count": null}, {"year": "1992", "bias_name": "Anti-Male", "count": null}, {"year": "1993", "bias_name": "Anti-Male", "count": null}, {"year": "1994", "bias_name": "Anti-Male", "count": null}, {"year": "1995", "bias_name": "Anti-Male", "count": null}, {"year": "1996", "bias_name": "Anti-Male", "count": null}, {"year": "1997", "bias_name": "Anti-Male", "count": null}, {"year": "1998", "bias_name": "Anti-Male", "count": null}, {"year": "1999", "bias_name": "Anti-Male", "count": null}, {"year": "2000", "bias_name": "Anti-Male", "count": null}, {"year": "2001", "bias_name": "Anti-Male", "count": null}, {"year": "2002", "bias_name": "Anti-Male", "count": null}, {"year": "2003", "bias_name": "Anti-Male", "count": null}, {"year": "2004", "bias_name": "Anti-Male", "count": null}, {"year": "2005", "bias_name": "Anti-Male", "count": null}, {"year": "2006", "bias_name": "Anti-Male", "count": null}, {"year": "2007", "bias_name": "Anti-Male", "count": null}, {"year": "2008", "bias_name": "Anti-Male", "count": null}, {"year": "2009", "bias_name": "Anti-Male", "count": null}, {"year": "2010", "bias_name": "Anti-Male", "count": null}, {"year": "2011", "bias_name": "Anti-Male", "count": null}, {"year": "2012", "bias_name": "Anti-Male", "count": null}, {"year": "2013", "bias_name": "Anti-Male", "count": null}, {"year": "2014", "bias_name": "Anti-Male", "count": null}, {"year": "2015", "bias_name": "Anti-Male", "count": null}, {"year": "2016", "bias_name": "Anti-Male", "count": null}, {"year": "2016", "bias_name": "Anti-Male Homosexual (Gay)", "count": null}, {"year": "1991", "bias_name": "Anti-Mental Disability", "count": null}, {"year": "1992", "bias_name": "Anti-Mental Disability", "count": null}, {"year": "1993", "bias_name": "Anti-Mental Disability", "count": null}, {"year": "1994", "bias_name": "Anti-Mental Disability", "count": null}, {"year": "1995", "bias_name": "Anti-Mental Disability", "count": null}, {"year": "1996", "bias_name": "Anti-Mental Disability", "count": null}, {"year": "1999", "bias_name": "Anti-Mental Disability", "count": null}, {"year": "2000", "bias_name": "Anti-Mental Disability", "count": null}, {"year": "2001", "bias_name": "Anti-Mental Disability", "count": null}, {"year": "2002", "bias_name": "Anti-Mental Disability", "count": null}, {"year": "2003", "bias_name": "Anti-Mental Disability", "count": null}, {"year": "2005", "bias_name": "Anti-Mental Disability", "count": null}, {"year": "2007", "bias_name": "Anti-Mental Disability", "count": null}, {"year": "2008", "bias_name": "Anti-Mental Disability", "count": null}, {"year": "2009", "bias_name": "Anti-Mental Disability", "count": null}, {"year": "2012", "bias_name": "Anti-Mental Disability", "count": null}, {"year": "2014", "bias_name": "Anti-Mental Disability", "count": null}, {"year": "2016", "bias_name": "Anti-Mental Disability", "count": null}, {"year": "1991", "bias_name": "Anti-Mormon", "count": null}, {"year": "1992", "bias_name": "Anti-Mormon", "count": null}, {"year": "1993", "bias_name": "Anti-Mormon", "count": null}, {"year": "1994", "bias_name": "Anti-Mormon", "count": null}, {"year": "1995", "bias_name": "Anti-Mormon", "count": null}, {"year": "1996", "bias_name": "Anti-Mormon", "count": null}, {"year": "1997", "bias_name": "Anti-Mormon", "count": null}, {"year": "1998", "bias_name": "Anti-Mormon", "count": null}, {"year": "1999", "bias_name": "Anti-Mormon", "count": null}, {"year": "2000", "bias_name": "Anti-Mormon", "count": null}, {"year": "2001", "bias_name": "Anti-Mormon", "count": null}, {"year": "2002", "bias_name": "Anti-Mormon", "count": null}, {"year": "2003", "bias_name": "Anti-Mormon", "count": null}, {"year": "2004", "bias_name": "Anti-Mormon", "count": null}, {"year": "2005", "bias_name": "Anti-Mormon", "count": null}, {"year": "2006", "bias_name": "Anti-Mormon", "count": null}, {"year": "2007", "bias_name": "Anti-Mormon", "count": null}, {"year": "2008", "bias_name": "Anti-Mormon", "count": null}, {"year": "2009", "bias_name": "Anti-Mormon", "count": null}, {"year": "2010", "bias_name": "Anti-Mormon", "count": null}, {"year": "2011", "bias_name": "Anti-Mormon", "count": null}, {"year": "2012", "bias_name": "Anti-Mormon", "count": null}, {"year": "2013", "bias_name": "Anti-Mormon", "count": null}, {"year": "2014", "bias_name": "Anti-Mormon", "count": null}, {"year": "2015", "bias_name": "Anti-Mormon", "count": null}, {"year": "2016", "bias_name": "Anti-Mormon", "count": null}, {"year": "1991", "bias_name": "Anti-Multi-Racial Group", "count": null}, {"year": "2011", "bias_name": "Anti-Multi-Racial Group", "count": null}, {"year": "2014", "bias_name": "Anti-Multi-Racial Group", "count": null}, {"year": "2016", "bias_name": "Anti-Multi-Racial Group", "count": null}, {"year": "1991", "bias_name": "Anti-Multi-Religious Group", "count": null}, {"year": "1993", "bias_name": "Anti-Multi-Religious Group", "count": null}, {"year": "1995", "bias_name": "Anti-Multi-Religious Group", "count": null}, {"year": "1996", "bias_name": "Anti-Multi-Religious Group", "count": null}, {"year": "2007", "bias_name": "Anti-Multi-Religious Group", "count": null}, {"year": "2008", "bias_name": "Anti-Multi-Religious Group", "count": null}, {"year": "2012", "bias_name": "Anti-Multi-Religious Group", "count": null}, {"year": "2013", "bias_name": "Anti-Multi-Religious Group", "count": null}, {"year": "2016", "bias_name": "Anti-Multi-Religious Group", "count": null}, {"year": "1991", "bias_name": "Anti-Native Hawaiian or Other Pacific Islander", "count": null}, {"year": "1992", "bias_name": "Anti-Native Hawaiian or Other Pacific Islander", "count": null}, {"year": "1993", "bias_name": "Anti-Native Hawaiian or Other Pacific Islander", "count": null}, {"year": "1994", "bias_name": "Anti-Native Hawaiian or Other Pacific Islander", "count": null}, {"year": "1995", "bias_name": "Anti-Native Hawaiian or Other Pacific Islander", "count": null}, {"year": "1996", "bias_name": "Anti-Native Hawaiian or Other Pacific Islander", "count": null}, {"year": "1997", "bias_name": "Anti-Native Hawaiian or Other Pacific Islander", "count": null}, {"year": "1998", "bias_name": "Anti-Native Hawaiian or Other Pacific Islander", "count": null}, {"year": "1999", "bias_name": "Anti-Native Hawaiian or Other Pacific Islander", "count": null}, {"year": "2000", "bias_name": "Anti-Native Hawaiian or Other Pacific Islander", "count": null}, {"year": "2001", "bias_name": "Anti-Native Hawaiian or Other Pacific Islander", "count": null}, {"year": "2002", "bias_name": "Anti-Native Hawaiian or Other Pacific Islander", "count": null}, {"year": "2003", "bias_name": "Anti-Native Hawaiian or Other Pacific Islander", "count": null}, {"year": "2004", "bias_name": "Anti-Native Hawaiian or Other Pacific Islander", "count": null}, {"year": "2005", "bias_name": "Anti-Native Hawaiian or Other Pacific Islander", "count": null}, {"year": "2006", "bias_name": "Anti-Native Hawaiian or Other Pacific Islander", "count": null}, {"year": "2007", "bias_name": "Anti-Native Hawaiian or Other Pacific Islander", "count": null}, {"year": "2008", "bias_name": "Anti-Native Hawaiian or Other Pacific Islander", "count": null}, {"year": "2009", "bias_name": "Anti-Native Hawaiian or Other Pacific Islander", "count": null}, {"year": "2010", "bias_name": "Anti-Native Hawaiian or Other Pacific Islander", "count": null}, {"year": "2011", "bias_name": "Anti-Native Hawaiian or Other Pacific Islander", "count": null}, {"year": "2012", "bias_name": "Anti-Native Hawaiian or Other Pacific Islander", "count": null}, {"year": "2013", "bias_name": "Anti-Native Hawaiian or Other Pacific Islander", "count": null}, {"year": "2014", "bias_name": "Anti-Native Hawaiian or Other Pacific Islander", "count": null}, {"year": "2015", "bias_name": "Anti-Native Hawaiian or Other Pacific Islander", "count": null}, {"year": "2016", "bias_name": "Anti-Native Hawaiian or Other Pacific Islander", "count": null}, {"year": "1999", "bias_name": "Anti-Not Hispanic or Latino", "count": null}, {"year": "2016", "bias_name": "Anti-Not Hispanic or Latino", "count": null}, {"year": "1991", "bias_name": "Anti-Other Christian", "count": null}, {"year": "1992", "bias_name": "Anti-Other Christian", "count": null}, {"year": "1993", "bias_name": "Anti-Other Christian", "count": null}, {"year": "1994", "bias_name": "Anti-Other Christian", "count": null}, {"year": "1995", "bias_name": "Anti-Other Christian", "count": null}, {"year": "1996", "bias_name": "Anti-Other Christian", "count": null}, {"year": "1997", "bias_name": "Anti-Other Christian", "count": null}, {"year": "1998", "bias_name": "Anti-Other Christian", "count": null}, {"year": "1999", "bias_name": "Anti-Other Christian", "count": null}, {"year": "2000", "bias_name": "Anti-Other Christian", "count": null}, {"year": "2001", "bias_name": "Anti-Other Christian", "count": null}], "pagination": {"per_page": 10, "count": 1, "page": 1, "pages": 1}}
